redis5/__init__.py
redis5/backoff.py
redis5/client.py
redis5/cluster.py
redis5/compat.py
redis5/connection.py
redis5/crc.py
redis5/credentials.py
redis5/exceptions.py
redis5/lock.py
redis5/ocsp.py
redis5/retry.py
redis5/sentinel.py
redis5/typing.py
redis5/utils.py
redis5/_parsers/__init__.py
redis5/_parsers/base.py
redis5/_parsers/commands.py
redis5/_parsers/encoders.py
redis5/_parsers/helpers.py
redis5/_parsers/hiredis.py
redis5/_parsers/resp2.py
redis5/_parsers/resp3.py
redis5/_parsers/socket.py
redis5/asyncio/__init__.py
redis5/asyncio/client.py
redis5/asyncio/cluster.py
redis5/asyncio/connection.py
redis5/asyncio/lock.py
redis5/asyncio/retry.py
redis5/asyncio/sentinel.py
redis5/asyncio/utils.py
redis5/commands/__init__.py
redis5/commands/cluster.py
redis5/commands/core.py
redis5/commands/helpers.py
redis5/commands/redismodules.py
redis5/commands/sentinel.py
redis5/commands/bf/__init__.py
redis5/commands/bf/commands.py
redis5/commands/bf/info.py
redis5/commands/graph/__init__.py
redis5/commands/graph/commands.py
redis5/commands/graph/edge.py
redis5/commands/graph/exceptions.py
redis5/commands/graph/execution_plan.py
redis5/commands/graph/node.py
redis5/commands/graph/path.py
redis5/commands/graph/query_result.py
redis5/commands/json/__init__.py
redis5/commands/json/_util.py
redis5/commands/json/commands.py
redis5/commands/json/decoders.py
redis5/commands/json/path.py
redis5/commands/search/__init__.py
redis5/commands/search/_util.py
redis5/commands/search/aggregation.py
redis5/commands/search/commands.py
redis5/commands/search/document.py
redis5/commands/search/field.py
redis5/commands/search/indexDefinition.py
redis5/commands/search/query.py
redis5/commands/search/querystring.py
redis5/commands/search/reducers.py
redis5/commands/search/result.py
redis5/commands/search/suggestion.py
redis5/commands/timeseries/__init__.py
redis5/commands/timeseries/commands.py
redis5/commands/timeseries/info.py
redis5/commands/timeseries/utils.py
redis5-5.0.0.1.dist-info/LICENSE
redis5-5.0.0.1.dist-info/METADATA
redis5-5.0.0.1.dist-info/WHEEL
redis5-5.0.0.1.dist-info/top_level.txt
redis5-5.0.0.1.dist-info/RECORD
